LordFile/__init__.py
LordFile/dataset.py
LordFile/filefolderclass.py
LordFile/opener.py
LordFile/zipping.py
LordFile-2023.3.5.dist-info/METADATA
LordFile-2023.3.5.dist-info/WHEEL
LordFile-2023.3.5.dist-info/top_level.txt
LordFile-2023.3.5.dist-info/RECORD
