Metadata-Version: 2.1
Name: LordFile
Version: 2023.3.5
Summary: Helper Package for other Lord packages
Author-email: lordbex <lordibex@protonmail.com>
Maintainer-email: lordbex <lordibex@protonmail.com>
Project-URL: homepage, https://git.lordbex.xyz/PipModule/LordFile
Project-URL: repository, https://git.lordbex.xyz/PipModule/LordFile
Requires-Python: >=3.10
Requires-Dist: regex
Requires-Dist: pyyaml
Requires-Dist: LordUtils
